shared_package_lentinis/__init__.py
shared_package_lentinis/postgres_engine.py
shared_package_lentinis/postgres_models.py
shared_package_lentinis-1.0.28.dist-info/METADATA
shared_package_lentinis-1.0.28.dist-info/WHEEL
shared_package_lentinis-1.0.28.dist-info/top_level.txt
shared_package_lentinis-1.0.28.dist-info/RECORD
