Metadata-Version: 2.2
Name: shared-package-lentinis
Version: 1.0.28
Summary: A shared utilities package
Requires-Dist: fastapi
